dglab2018/__init__.py
dglab2018-0.0.16.dist-info/METADATA
dglab2018-0.0.16.dist-info/RECORD
dglab2018-0.0.16.dist-info/WHEEL
dglab2018-0.0.16.dist-info/top_level.txt
