Metadata-Version: 2.1
Name: dglab2018
Version: 0.0.16
Summary: Data processing and analysis scripts supporting the PhD project by one Dominik Gotojuch
Home-page: https://github.com/robotgentleman/dglab2018
Author: Dominik Gotojuch
Author-email: dominik@gotojuch.com
License: UNKNOWN
Platform: UNKNOWN
Classifier: Programming Language :: Python :: 3
Classifier: License :: OSI Approved :: MIT License
Classifier: Operating System :: OS Independent
